portfolio/__init__.py
portfolio/admin.py
portfolio/apps.py
portfolio/models.py
portfolio/urls.py
portfolio/views.py
portfolio/static/css/portfolio/bethany_ds.css
portfolio/static/css/portfolio/medilab_ds.css
portfolio/static/css/portfolio_details/bethany_ds.css
portfolio/static/css/portfolio_details/medilab_ds.css
portfolio/static/js/portfolio_slider.js
portfolio/templates/portfolio/_common.html
portfolio/templates/portfolio/bethany_ds.html
portfolio/templates/portfolio/medilab_ds.html
portfolio/templates/portfolio_details/details.html
portfolio/templatetags/__init__.py
portfolio/templatetags/portfolio_tags.py
django_portfolio_ds-1.0.1.dist-info/LICENSE
django_portfolio_ds-1.0.1.dist-info/METADATA
django_portfolio_ds-1.0.1.dist-info/WHEEL
django_portfolio_ds-1.0.1.dist-info/top_level.txt
django_portfolio_ds-1.0.1.dist-info/RECORD
