Metadata-Version: 2.1
Name: django-portfolio-ds
Version: 1.0.1
Summary: portfolio part for demiansoft
Home-page: https://www.demiansoft.com
Author: hyungjin kim
Author-email: hj3415@gmail.com
Project-URL: Bug Tracker, https://pypi.org/project/util-demian/
Classifier: License :: OSI Approved :: BSD License
Classifier: Operating System :: OS Independent
Classifier: Programming Language :: Python :: 3
Requires-Python: >=3.8
License-File: LICENSE
Requires-Dist: Django (>=3.2.9)
Requires-Dist: Pillow (>=9.1.0)
Requires-Dist: django-base-ds (>=0.0.3)
